minidi/__init__.py
minidi-1.1.1.dist-info/LICENSE
minidi-1.1.1.dist-info/METADATA
minidi-1.1.1.dist-info/WHEEL
minidi-1.1.1.dist-info/top_level.txt
minidi-1.1.1.dist-info/RECORD
