Metadata-Version: 2.1
Name: minidi
Version: 1.1.1
Summary: A minimalistic and easy to use Dependency Injection Framework.
Home-page: https://gitlab.com/axelalex2/minidi
Author: axelalex2
Author-email: axelalex2@gmx.de
License: UNKNOWN
Project-URL: Bug Tracker, https://gitlab.com/axelalex2/minidi/-/issues
Platform: UNKNOWN
Classifier: Programming Language :: Python :: 3
Classifier: License :: OSI Approved :: GNU General Public License v3 (GPLv3)
Classifier: Operating System :: OS Independent
Requires-Python: >=3.4
License-File: LICENSE
